copyacross/__init__.py
copyacross/cli.py
copyacross/config.py
copyacross/exceptions.py
copyacross/logger.py
copyacross/sync_engine.py
copyacross/transport.py
copyacross/verifier.py
copyacross-0.1.0.dist-info/licenses/LICENSE
copyacross-0.1.0.dist-info/METADATA
copyacross-0.1.0.dist-info/WHEEL
copyacross-0.1.0.dist-info/entry_points.txt
copyacross-0.1.0.dist-info/top_level.txt
copyacross-0.1.0.dist-info/RECORD
