Metadata-Version: 2.4
Name: copyacross
Version: 0.1.0
Summary: Cross-platform file copy & verification tool
Home-page: https://github.com/compilersutra/copyacross
Author: Tiwari Abhinav Ashok Kumar
Author-email: Compilersutra <osc@compilersutra.com>
License: MIT
Project-URL: Homepage, https://github.com/compilersutra/copyacross
Project-URL: Source, https://github.com/compilersutra/copyacross
Project-URL: Issues, https://github.com/compilersutra/copyacross/issues
Keywords: scp,file-transfer,sync,ssh,verification,devops
Requires-Python: >=3.8
License-File: LICENSE
Requires-Dist: click>=8.0
Requires-Dist: paramiko>=3.0
Requires-Dist: pyyaml>=6.0
Dynamic: license-file
